codf/__init__.py
codf-0.0.0.dist-info/LICENSE
codf-0.0.0.dist-info/METADATA
codf-0.0.0.dist-info/WHEEL
codf-0.0.0.dist-info/top_level.txt
codf-0.0.0.dist-info/RECORD
