Metadata-Version: 2.1
Name: codf
Version: 0.0.0
Summary: Cardinal Operations Demand Forecast
Author: ['CODF Developers']
License-File: LICENSE
